setup.py
ast_drawer/__init__.py
ast_drawer/fib.py
ast_drawer/main.py
ast_drawer/printer.py
nikolay_egorov_python_2022_hw1.egg-info/PKG-INFO
nikolay_egorov_python_2022_hw1.egg-info/SOURCES.txt
nikolay_egorov_python_2022_hw1.egg-info/dependency_links.txt
nikolay_egorov_python_2022_hw1.egg-info/not-zip-safe
nikolay_egorov_python_2022_hw1.egg-info/top_level.txt