Metadata-Version: 2.1
Name: nikolay-egorov-python-2022-hw1
Version: 0.1.4
Summary: AST builder and drawer for a simple function 
Home-page: UNKNOWN
Author: Nikolay.Egorov
Author-email: deathadder98@gmail.com
License: BST
Platform: UNKNOWN
